<?xml version="1.0" encoding="UTF-8"?>
<departamentos><departamento><codDpto>AER</codDpto><descDpto>Aeronautica</descDpto></departamento><departamento><codDpto>ALE</codDpto><descDpto>Aleman</descDpto></departamento><departamento><codDpto>AUT</codDpto><descDpto>Automoción</descDpto></departamento><departamento><codDpto>CHI</codDpto><descDpto>Chino</descDpto></departamento><departamento><codDpto>DEF</codDpto><descDpto>Defensa</descDpto></departamento><departamento><codDpto>FRA</codDpto><descDpto>Francés</descDpto></departamento><departamento><codDpto>HJK</codDpto><descDpto>hhhhhhhhhhhhhhhhhhhhhhhh</descDpto></departamento><departamento><codDpto>ING</codDpto><descDpto>Ingles</descDpto></departamento><departamento><codDpto>ITA</codDpto><descDpto>Italiano</descDpto></departamento><departamento><codDpto>RUS</codDpto><descDpto>Ruso</descDpto></departamento></departamentos>
